{
  "unitid": 101189004,
  "name": "Faulkner University",
  "shortName": null,
  "city": "MOBILE",
  "state": "AL",
  "ivyLeague": false,
  "isMainCampus": false,
  "campusType": "Branch Campus",
  "fte": 2728,
  "fteByYear": {
    "2017": 2728
  },
  "summary": {
    "latestYear": 2017,
    "totalIncidents": 99,
    "topOffense": "Domestic Violence",
    "topOffenseCount": 57
  },
  "yearlyTotals": [
    {
      "year": 2017,
      "total": 99
    }
  ],
  "trends": [
    {
      "year": 2017,
      "offense": "Arson",
      "offenseFamily": "Criminal",
      "count": 3
    },
    {
      "year": 2017,
      "offense": "Domestic Violence",
      "offenseFamily": "VAWA",
      "count": 57
    },
    {
      "year": 2017,
      "offense": "Drug Arrest",
      "offenseFamily": "Arrest",
      "count": 15
    },
    {
      "year": 2017,
      "offense": "Liquor Arrest",
      "offenseFamily": "Arrest",
      "count": 15
    },
    {
      "year": 2017,
      "offense": "Motor Vehicle Theft",
      "offenseFamily": "Criminal",
      "count": 3
    },
    {
      "year": 2017,
      "offense": "Weapons Arrest",
      "offenseFamily": "Arrest",
      "count": 6
    }
  ],
  "breakdownByOffense": [
    {
      "offense": "Domestic Violence",
      "count": 57
    },
    {
      "offense": "Drug Arrest",
      "count": 15
    },
    {
      "offense": "Liquor Arrest",
      "count": 15
    },
    {
      "offense": "Weapons Arrest",
      "count": 6
    },
    {
      "offense": "Arson",
      "count": 3
    },
    {
      "offense": "Motor Vehicle Theft",
      "count": 3
    }
  ],
  "breakdownByGeo": [
    {
      "geo": "Public property",
      "count": 99
    }
  ]
}