{
  "unitid": 131803001,
  "name": "Strayer University-District of Columbia",
  "shortName": null,
  "city": "WASHINGTON",
  "state": "DC",
  "ivyLeague": false,
  "isMainCampus": true,
  "campusType": "Main Campus",
  "fte": 459,
  "fteByYear": {
    "2015": 601,
    "2016": 565,
    "2018": 459
  },
  "summary": {
    "latestYear": 2018,
    "totalIncidents": 1,
    "topOffense": "Drug Arrest",
    "topOffenseCount": 1
  },
  "yearlyTotals": [
    {
      "year": 2015,
      "total": 3
    },
    {
      "year": 2016,
      "total": 3
    },
    {
      "year": 2018,
      "total": 1
    }
  ],
  "trends": [
    {
      "year": 2015,
      "offense": "Weapons Arrest",
      "offenseFamily": "Arrest",
      "count": 3
    },
    {
      "year": 2016,
      "offense": "Aggravated Assault",
      "offenseFamily": "Criminal",
      "count": 3
    },
    {
      "year": 2018,
      "offense": "Drug Arrest",
      "offenseFamily": "Arrest",
      "count": 1
    }
  ],
  "breakdownByOffense": [
    {
      "offense": "Drug Arrest",
      "count": 1
    }
  ],
  "breakdownByGeo": [
    {
      "geo": "Public property",
      "count": 1
    }
  ]
}