{
  "unitid": 139010001,
  "name": "Bainbridge State College",
  "shortName": null,
  "city": "BAINBRIDGE",
  "state": "GA",
  "ivyLeague": false,
  "isMainCampus": true,
  "campusType": "Main Campus",
  "fte": 997,
  "fteByYear": {
    "2016": 1471,
    "2017": 997
  },
  "summary": {
    "latestYear": 2017,
    "totalIncidents": 1,
    "topOffense": "Burglary",
    "topOffenseCount": 1
  },
  "yearlyTotals": [
    {
      "year": 2016,
      "total": 8
    },
    {
      "year": 2017,
      "total": 1
    }
  ],
  "trends": [
    {
      "year": 2016,
      "offense": "Drug Arrest",
      "offenseFamily": "Arrest",
      "count": 4
    },
    {
      "year": 2016,
      "offense": "Fondling",
      "offenseFamily": "Criminal",
      "count": 4
    },
    {
      "year": 2017,
      "offense": "Burglary",
      "offenseFamily": "Criminal",
      "count": 1
    }
  ],
  "breakdownByOffense": [
    {
      "offense": "Burglary",
      "count": 1
    }
  ],
  "breakdownByGeo": [
    {
      "geo": "On-campus",
      "count": 1
    }
  ]
}