{
  "unitid": 140818001,
  "name": "Piedmont College",
  "shortName": null,
  "city": "DEMOREST",
  "state": "GA",
  "ivyLeague": false,
  "isMainCampus": true,
  "campusType": "Main Campus",
  "fte": 1505,
  "fteByYear": {
    "2015": 1759,
    "2016": 1818,
    "2017": 1846,
    "2018": 1960,
    "2019": 1940,
    "2020": 1885,
    "2021": 1670,
    "2022": 1488,
    "2023": 1505
  },
  "summary": {
    "latestYear": 2023,
    "totalIncidents": 34,
    "topOffense": "Stalking",
    "topOffenseCount": 11
  },
  "yearlyTotals": [
    {
      "year": 2015,
      "total": 135
    },
    {
      "year": 2016,
      "total": 144
    },
    {
      "year": 2017,
      "total": 75
    },
    {
      "year": 2018,
      "total": 120
    },
    {
      "year": 2019,
      "total": 147
    },
    {
      "year": 2020,
      "total": 135
    },
    {
      "year": 2021,
      "total": 51
    },
    {
      "year": 2022,
      "total": 30
    },
    {
      "year": 2023,
      "total": 34
    }
  ],
  "trends": [
    {
      "year": 2015,
      "offense": "Drug Arrest",
      "offenseFamily": "Arrest",
      "count": 6
    },
    {
      "year": 2015,
      "offense": "Drug Discipline",
      "offenseFamily": "Disciplinary",
      "count": 9
    },
    {
      "year": 2015,
      "offense": "Liquor Arrest",
      "offenseFamily": "Arrest",
      "count": 3
    },
    {
      "year": 2015,
      "offense": "Liquor Discipline",
      "offenseFamily": "Disciplinary",
      "count": 117
    },
    {
      "year": 2016,
      "offense": "Burglary",
      "offenseFamily": "Criminal",
      "count": 3
    },
    {
      "year": 2016,
      "offense": "Dating Violence",
      "offenseFamily": "VAWA",
      "count": 3
    },
    {
      "year": 2016,
      "offense": "Drug Arrest",
      "offenseFamily": "Arrest",
      "count": 15
    },
    {
      "year": 2016,
      "offense": "Drug Discipline",
      "offenseFamily": "Disciplinary",
      "count": 15
    },
    {
      "year": 2016,
      "offense": "Liquor Arrest",
      "offenseFamily": "Arrest",
      "count": 9
    },
    {
      "year": 2016,
      "offense": "Liquor Discipline",
      "offenseFamily": "Disciplinary",
      "count": 96
    },
    {
      "year": 2016,
      "offense": "Rape",
      "offenseFamily": "Criminal",
      "count": 3
    },
    {
      "year": 2017,
      "offense": "Drug Discipline",
      "offenseFamily": "Disciplinary",
      "count": 42
    },
    {
      "year": 2017,
      "offense": "Liquor Discipline",
      "offenseFamily": "Disciplinary",
      "count": 33
    },
    {
      "year": 2018,
      "offense": "Drug Discipline",
      "offenseFamily": "Disciplinary",
      "count": 30
    },
    {
      "year": 2018,
      "offense": "Liquor Discipline",
      "offenseFamily": "Disciplinary",
      "count": 90
    },
    {
      "year": 2019,
      "offense": "Drug Discipline",
      "offenseFamily": "Disciplinary",
      "count": 33
    },
    {
      "year": 2019,
      "offense": "Fondling",
      "offenseFamily": "Criminal",
      "count": 3
    },
    {
      "year": 2019,
      "offense": "Liquor Discipline",
      "offenseFamily": "Disciplinary",
      "count": 102
    },
    {
      "year": 2019,
      "offense": "Rape",
      "offenseFamily": "Criminal",
      "count": 9
    },
    {
      "year": 2020,
      "offense": "Drug Discipline",
      "offenseFamily": "Disciplinary",
      "count": 18
    },
    {
      "year": 2020,
      "offense": "Liquor Discipline",
      "offenseFamily": "Disciplinary",
      "count": 117
    },
    {
      "year": 2021,
      "offense": "Dating Violence",
      "offenseFamily": "VAWA",
      "count": 3
    },
    {
      "year": 2021,
      "offense": "Drug Arrest",
      "offenseFamily": "Arrest",
      "count": 6
    },
    {
      "year": 2021,
      "offense": "Drug Discipline",
      "offenseFamily": "Disciplinary",
      "count": 3
    },
    {
      "year": 2021,
      "offense": "Fondling",
      "offenseFamily": "Criminal",
      "count": 3
    },
    {
      "year": 2021,
      "offense": "Liquor Discipline",
      "offenseFamily": "Disciplinary",
      "count": 33
    },
    {
      "year": 2021,
      "offense": "Rape",
      "offenseFamily": "Criminal",
      "count": 3
    },
    {
      "year": 2022,
      "offense": "Dating Violence",
      "offenseFamily": "VAWA",
      "count": 10
    },
    {
      "year": 2022,
      "offense": "Drug Discipline",
      "offenseFamily": "Disciplinary",
      "count": 2
    },
    {
      "year": 2022,
      "offense": "Liquor Discipline",
      "offenseFamily": "Disciplinary",
      "count": 10
    },
    {
      "year": 2022,
      "offense": "Rape",
      "offenseFamily": "Criminal",
      "count": 2
    },
    {
      "year": 2022,
      "offense": "Robbery",
      "offenseFamily": "Criminal",
      "count": 4
    },
    {
      "year": 2022,
      "offense": "Stalking",
      "offenseFamily": "VAWA",
      "count": 2
    },
    {
      "year": 2023,
      "offense": "Burglary",
      "offenseFamily": "Criminal",
      "count": 1
    },
    {
      "year": 2023,
      "offense": "Dating Violence",
      "offenseFamily": "VAWA",
      "count": 3
    },
    {
      "year": 2023,
      "offense": "Drug Arrest",
      "offenseFamily": "Arrest",
      "count": 1
    },
    {
      "year": 2023,
      "offense": "Drug Discipline",
      "offenseFamily": "Disciplinary",
      "count": 7
    },
    {
      "year": 2023,
      "offense": "Liquor Arrest",
      "offenseFamily": "Arrest",
      "count": 9
    },
    {
      "year": 2023,
      "offense": "Liquor Discipline",
      "offenseFamily": "Disciplinary",
      "count": 2
    },
    {
      "year": 2023,
      "offense": "Stalking",
      "offenseFamily": "VAWA",
      "count": 11
    }
  ],
  "breakdownByOffense": [
    {
      "offense": "Stalking",
      "count": 11
    },
    {
      "offense": "Liquor Arrest",
      "count": 9
    },
    {
      "offense": "Drug Discipline",
      "count": 7
    },
    {
      "offense": "Dating Violence",
      "count": 3
    },
    {
      "offense": "Liquor Discipline",
      "count": 2
    },
    {
      "offense": "Burglary",
      "count": 1
    },
    {
      "offense": "Drug Arrest",
      "count": 1
    }
  ],
  "breakdownByGeo": [
    {
      "geo": "On-campus",
      "count": 34
    },
    {
      "geo": "Residence halls",
      "count": 22
    }
  ]
}