{
  "unitid": 141255001,
  "name": "Wiregrass Georgia Technical College",
  "shortName": null,
  "city": "Valdosta",
  "state": "GA",
  "ivyLeague": false,
  "isMainCampus": true,
  "campusType": "Main Campus",
  "fte": 2410,
  "fteByYear": {
    "2016": 2154,
    "2017": 2131,
    "2018": 2490,
    "2019": 2410
  },
  "summary": {
    "latestYear": 2019,
    "totalIncidents": 6,
    "topOffense": "Domestic Violence",
    "topOffenseCount": 3
  },
  "yearlyTotals": [
    {
      "year": 2016,
      "total": 9
    },
    {
      "year": 2017,
      "total": 6
    },
    {
      "year": 2018,
      "total": 3
    },
    {
      "year": 2019,
      "total": 6
    }
  ],
  "trends": [
    {
      "year": 2016,
      "offense": "Domestic Violence",
      "offenseFamily": "VAWA",
      "count": 6
    },
    {
      "year": 2016,
      "offense": "Drug Discipline",
      "offenseFamily": "Disciplinary",
      "count": 3
    },
    {
      "year": 2017,
      "offense": "Liquor Arrest",
      "offenseFamily": "Arrest",
      "count": 3
    },
    {
      "year": 2017,
      "offense": "Motor Vehicle Theft",
      "offenseFamily": "Criminal",
      "count": 3
    },
    {
      "year": 2018,
      "offense": "Weapons Arrest",
      "offenseFamily": "Arrest",
      "count": 3
    },
    {
      "year": 2019,
      "offense": "Domestic Violence",
      "offenseFamily": "VAWA",
      "count": 3
    },
    {
      "year": 2019,
      "offense": "Stalking",
      "offenseFamily": "VAWA",
      "count": 3
    }
  ],
  "breakdownByOffense": [
    {
      "offense": "Domestic Violence",
      "count": 3
    },
    {
      "offense": "Stalking",
      "count": 3
    }
  ],
  "breakdownByGeo": [
    {
      "geo": "Public property",
      "count": 6
    }
  ]
}