{
  "unitid": 170082002,
  "name": "Grand Valley State University",
  "shortName": null,
  "city": "Grand Rapids",
  "state": "MI",
  "ivyLeague": false,
  "isMainCampus": false,
  "campusType": "Branch Campus",
  "fte": 20170,
  "fteByYear": {
    "2015": 22533,
    "2016": 22780,
    "2017": 22429,
    "2018": 22211,
    "2019": 21680,
    "2020": 20966,
    "2021": 20029,
    "2022": 19453,
    "2023": 20170
  },
  "summary": {
    "latestYear": 2023,
    "totalIncidents": 24,
    "topOffense": "Weapons Arrest",
    "topOffenseCount": 8
  },
  "yearlyTotals": [
    {
      "year": 2015,
      "total": 24
    },
    {
      "year": 2016,
      "total": 24
    },
    {
      "year": 2017,
      "total": 39
    },
    {
      "year": 2018,
      "total": 30
    },
    {
      "year": 2019,
      "total": 30
    },
    {
      "year": 2020,
      "total": 24
    },
    {
      "year": 2021,
      "total": 30
    },
    {
      "year": 2022,
      "total": 38
    },
    {
      "year": 2023,
      "total": 24
    }
  ],
  "trends": [
    {
      "year": 2015,
      "offense": "Burglary",
      "offenseFamily": "Criminal",
      "count": 3
    },
    {
      "year": 2015,
      "offense": "Domestic Violence",
      "offenseFamily": "VAWA",
      "count": 3
    },
    {
      "year": 2015,
      "offense": "Drug Arrest",
      "offenseFamily": "Arrest",
      "count": 3
    },
    {
      "year": 2015,
      "offense": "Drug Discipline",
      "offenseFamily": "Disciplinary",
      "count": 3
    },
    {
      "year": 2015,
      "offense": "Robbery",
      "offenseFamily": "Criminal",
      "count": 12
    },
    {
      "year": 2016,
      "offense": "Burglary",
      "offenseFamily": "Criminal",
      "count": 3
    },
    {
      "year": 2016,
      "offense": "Fondling",
      "offenseFamily": "Criminal",
      "count": 3
    },
    {
      "year": 2016,
      "offense": "Liquor Arrest",
      "offenseFamily": "Arrest",
      "count": 3
    },
    {
      "year": 2016,
      "offense": "Stalking",
      "offenseFamily": "VAWA",
      "count": 15
    },
    {
      "year": 2017,
      "offense": "Aggravated Assault",
      "offenseFamily": "Criminal",
      "count": 3
    },
    {
      "year": 2017,
      "offense": "Burglary",
      "offenseFamily": "Criminal",
      "count": 3
    },
    {
      "year": 2017,
      "offense": "Drug Arrest",
      "offenseFamily": "Arrest",
      "count": 15
    },
    {
      "year": 2017,
      "offense": "Liquor Arrest",
      "offenseFamily": "Arrest",
      "count": 3
    },
    {
      "year": 2017,
      "offense": "Liquor Discipline",
      "offenseFamily": "Disciplinary",
      "count": 6
    },
    {
      "year": 2017,
      "offense": "Robbery",
      "offenseFamily": "Criminal",
      "count": 9
    },
    {
      "year": 2018,
      "offense": "Aggravated Assault",
      "offenseFamily": "Criminal",
      "count": 3
    },
    {
      "year": 2018,
      "offense": "Burglary",
      "offenseFamily": "Criminal",
      "count": 12
    },
    {
      "year": 2018,
      "offense": "Rape",
      "offenseFamily": "Criminal",
      "count": 6
    },
    {
      "year": 2018,
      "offense": "Stalking",
      "offenseFamily": "VAWA",
      "count": 9
    },
    {
      "year": 2019,
      "offense": "Dating Violence",
      "offenseFamily": "VAWA",
      "count": 3
    },
    {
      "year": 2019,
      "offense": "Fondling",
      "offenseFamily": "Criminal",
      "count": 3
    },
    {
      "year": 2019,
      "offense": "Rape",
      "offenseFamily": "Criminal",
      "count": 3
    },
    {
      "year": 2019,
      "offense": "Robbery",
      "offenseFamily": "Criminal",
      "count": 9
    },
    {
      "year": 2019,
      "offense": "Stalking",
      "offenseFamily": "VAWA",
      "count": 12
    },
    {
      "year": 2020,
      "offense": "Aggravated Assault",
      "offenseFamily": "Criminal",
      "count": 3
    },
    {
      "year": 2020,
      "offense": "Drug Arrest",
      "offenseFamily": "Arrest",
      "count": 3
    },
    {
      "year": 2020,
      "offense": "Liquor Arrest",
      "offenseFamily": "Arrest",
      "count": 3
    },
    {
      "year": 2020,
      "offense": "Motor Vehicle Theft",
      "offenseFamily": "Criminal",
      "count": 3
    },
    {
      "year": 2020,
      "offense": "Stalking",
      "offenseFamily": "VAWA",
      "count": 3
    },
    {
      "year": 2020,
      "offense": "Weapons Arrest",
      "offenseFamily": "Arrest",
      "count": 9
    },
    {
      "year": 2021,
      "offense": "Aggravated Assault",
      "offenseFamily": "Criminal",
      "count": 6
    },
    {
      "year": 2021,
      "offense": "Domestic Violence",
      "offenseFamily": "VAWA",
      "count": 3
    },
    {
      "year": 2021,
      "offense": "Fondling",
      "offenseFamily": "Criminal",
      "count": 3
    },
    {
      "year": 2021,
      "offense": "Motor Vehicle Theft",
      "offenseFamily": "Criminal",
      "count": 3
    },
    {
      "year": 2021,
      "offense": "Rape",
      "offenseFamily": "Criminal",
      "count": 3
    },
    {
      "year": 2021,
      "offense": "Robbery",
      "offenseFamily": "Criminal",
      "count": 3
    },
    {
      "year": 2021,
      "offense": "Stalking",
      "offenseFamily": "VAWA",
      "count": 6
    },
    {
      "year": 2021,
      "offense": "Weapons Arrest",
      "offenseFamily": "Arrest",
      "count": 3
    },
    {
      "year": 2022,
      "offense": "Aggravated Assault",
      "offenseFamily": "Criminal",
      "count": 8
    },
    {
      "year": 2022,
      "offense": "Burglary",
      "offenseFamily": "Criminal",
      "count": 2
    },
    {
      "year": 2022,
      "offense": "Dating Violence",
      "offenseFamily": "VAWA",
      "count": 6
    },
    {
      "year": 2022,
      "offense": "Domestic Violence",
      "offenseFamily": "VAWA",
      "count": 2
    },
    {
      "year": 2022,
      "offense": "Drug Discipline",
      "offenseFamily": "Disciplinary",
      "count": 2
    },
    {
      "year": 2022,
      "offense": "Fondling",
      "offenseFamily": "Criminal",
      "count": 2
    },
    {
      "year": 2022,
      "offense": "Motor Vehicle Theft",
      "offenseFamily": "Criminal",
      "count": 4
    },
    {
      "year": 2022,
      "offense": "Rape",
      "offenseFamily": "Criminal",
      "count": 4
    },
    {
      "year": 2022,
      "offense": "Robbery",
      "offenseFamily": "Criminal",
      "count": 4
    },
    {
      "year": 2022,
      "offense": "Stalking",
      "offenseFamily": "VAWA",
      "count": 2
    },
    {
      "year": 2022,
      "offense": "Weapons Arrest",
      "offenseFamily": "Arrest",
      "count": 2
    },
    {
      "year": 2023,
      "offense": "Aggravated Assault",
      "offenseFamily": "Criminal",
      "count": 1
    },
    {
      "year": 2023,
      "offense": "Burglary",
      "offenseFamily": "Criminal",
      "count": 3
    },
    {
      "year": 2023,
      "offense": "Domestic Violence",
      "offenseFamily": "VAWA",
      "count": 2
    },
    {
      "year": 2023,
      "offense": "Fondling",
      "offenseFamily": "Criminal",
      "count": 1
    },
    {
      "year": 2023,
      "offense": "Motor Vehicle Theft",
      "offenseFamily": "Criminal",
      "count": 3
    },
    {
      "year": 2023,
      "offense": "Robbery",
      "offenseFamily": "Criminal",
      "count": 2
    },
    {
      "year": 2023,
      "offense": "Stalking",
      "offenseFamily": "VAWA",
      "count": 4
    },
    {
      "year": 2023,
      "offense": "Weapons Arrest",
      "offenseFamily": "Arrest",
      "count": 8
    }
  ],
  "breakdownByOffense": [
    {
      "offense": "Weapons Arrest",
      "count": 8
    },
    {
      "offense": "Stalking",
      "count": 4
    },
    {
      "offense": "Burglary",
      "count": 3
    },
    {
      "offense": "Motor Vehicle Theft",
      "count": 3
    },
    {
      "offense": "Domestic Violence",
      "count": 2
    },
    {
      "offense": "Robbery",
      "count": 2
    },
    {
      "offense": "Aggravated Assault",
      "count": 1
    },
    {
      "offense": "Fondling",
      "count": 1
    }
  ],
  "breakdownByGeo": [
    {
      "geo": "On-campus",
      "count": 12
    },
    {
      "geo": "Public property",
      "count": 12
    },
    {
      "geo": "Residence halls",
      "count": 2
    }
  ]
}