{
  "unitid": 172699014,
  "name": "School 172699014",
  "shortName": null,
  "city": null,
  "state": null,
  "ivyLeague": false,
  "isMainCampus": false,
  "campusType": "Branch Campus",
  "fte": 14343,
  "fteByYear": {
    "2021": 15023,
    "2022": 14343
  },
  "summary": {
    "latestYear": 2022,
    "totalIncidents": 0,
    "topOffense": null,
    "topOffenseCount": 0
  },
  "yearlyTotals": [],
  "trends": [],
  "breakdownByOffense": [],
  "breakdownByGeo": [
    {
      "geo": "Public property",
      "count": 2
    }
  ]
}