{
  "unitid": 178721050,
  "name": "School 178721050",
  "shortName": null,
  "city": null,
  "state": null,
  "ivyLeague": false,
  "isMainCampus": false,
  "campusType": "Branch Campus",
  "fte": 7052,
  "fteByYear": {
    "2017": 7160,
    "2018": 7052
  },
  "summary": {
    "latestYear": 2018,
    "totalIncidents": 0,
    "topOffense": null,
    "topOffenseCount": 0
  },
  "yearlyTotals": [],
  "trends": [],
  "breakdownByOffense": [],
  "breakdownByGeo": [
    {
      "geo": "Public property",
      "count": 6
    }
  ]
}