{
  "unitid": 178721054,
  "name": "School 178721054",
  "shortName": null,
  "city": null,
  "state": null,
  "ivyLeague": false,
  "isMainCampus": false,
  "campusType": "Branch Campus",
  "fte": 5548,
  "fteByYear": {
    "2020": 6419,
    "2021": 5548
  },
  "summary": {
    "latestYear": 2021,
    "totalIncidents": 0,
    "topOffense": null,
    "topOffenseCount": 0
  },
  "yearlyTotals": [],
  "trends": [],
  "breakdownByOffense": [],
  "breakdownByGeo": [
    {
      "geo": "Public property",
      "count": 2
    }
  ]
}