{
  "unitid": 202648001,
  "name": "Edison State Community College",
  "shortName": null,
  "city": "PIQUA",
  "state": "OH",
  "ivyLeague": false,
  "isMainCampus": true,
  "campusType": "Main Campus",
  "fte": 1999,
  "fteByYear": {
    "2018": 1999
  },
  "summary": {
    "latestYear": 2018,
    "totalIncidents": 3,
    "topOffense": "Weapons Arrest",
    "topOffenseCount": 3
  },
  "yearlyTotals": [
    {
      "year": 2018,
      "total": 3
    }
  ],
  "trends": [
    {
      "year": 2018,
      "offense": "Weapons Arrest",
      "offenseFamily": "Arrest",
      "count": 3
    }
  ],
  "breakdownByOffense": [
    {
      "offense": "Weapons Arrest",
      "count": 3
    }
  ],
  "breakdownByGeo": [
    {
      "geo": "On-campus",
      "count": 3
    }
  ]
}