{
  "unitid": 233842001,
  "name": "Union Presbyterian Seminary",
  "shortName": null,
  "city": "Richmond",
  "state": "VA",
  "ivyLeague": false,
  "isMainCampus": true,
  "campusType": "Main Campus",
  "fte": 137,
  "fteByYear": {
    "2016": 117,
    "2020": 112,
    "2023": 137
  },
  "summary": {
    "latestYear": 2023,
    "totalIncidents": 1,
    "topOffense": "Weapons Arrest",
    "topOffenseCount": 1
  },
  "yearlyTotals": [
    {
      "year": 2016,
      "total": 3
    },
    {
      "year": 2020,
      "total": 2
    },
    {
      "year": 2023,
      "total": 1
    }
  ],
  "trends": [
    {
      "year": 2016,
      "offense": "Burglary",
      "offenseFamily": "Criminal",
      "count": 3
    },
    {
      "year": 2020,
      "offense": "Motor Vehicle Theft",
      "offenseFamily": "Criminal",
      "count": 2
    },
    {
      "year": 2023,
      "offense": "Weapons Arrest",
      "offenseFamily": "Arrest",
      "count": 1
    }
  ],
  "breakdownByOffense": [
    {
      "offense": "Weapons Arrest",
      "count": 1
    }
  ],
  "breakdownByGeo": [
    {
      "geo": "Public property",
      "count": 1
    }
  ]
}