{
  "unitid": 440402004,
  "name": "School 440402004",
  "shortName": null,
  "city": null,
  "state": null,
  "ivyLeague": false,
  "isMainCampus": false,
  "campusType": "Branch Campus",
  "fte": 1033,
  "fteByYear": {
    "2017": 1667,
    "2018": 1536,
    "2021": 1098,
    "2022": 910,
    "2023": 1033
  },
  "summary": {
    "latestYear": 2023,
    "totalIncidents": 0,
    "topOffense": null,
    "topOffenseCount": 0
  },
  "yearlyTotals": [],
  "trends": [],
  "breakdownByOffense": [],
  "breakdownByGeo": [
    {
      "geo": "Public property",
      "count": 2
    }
  ]
}