{
  "unitid": 495147001,
  "name": "School 495147001",
  "shortName": null,
  "city": null,
  "state": null,
  "ivyLeague": false,
  "isMainCampus": true,
  "campusType": "Main Campus",
  "fte": 125,
  "fteByYear": {
    "2020": 33,
    "2023": 125
  },
  "summary": {
    "latestYear": 2023,
    "totalIncidents": 0,
    "topOffense": null,
    "topOffenseCount": 0
  },
  "yearlyTotals": [],
  "trends": [],
  "breakdownByOffense": [],
  "breakdownByGeo": [
    {
      "geo": "On-campus",
      "count": 1
    },
    {
      "geo": "Public property",
      "count": 1
    }
  ]
}