{
  "unitid": 498562010,
  "name": "School 498562010",
  "shortName": null,
  "city": null,
  "state": null,
  "ivyLeague": false,
  "isMainCampus": false,
  "campusType": "Branch Campus",
  "fte": 10106,
  "fteByYear": {
    "2022": 10691,
    "2023": 10106
  },
  "summary": {
    "latestYear": 2023,
    "totalIncidents": 0,
    "topOffense": null,
    "topOffenseCount": 0
  },
  "yearlyTotals": [],
  "trends": [],
  "breakdownByOffense": [],
  "breakdownByGeo": [
    {
      "geo": "On-campus",
      "count": 2
    },
    {
      "geo": "Public property",
      "count": 2
    }
  ]
}